linea_cli/__init__.py
linea_cli/cli.py
linea_cli/libs/__init__.py
linea_cli/libs/client.py
linea_cli/libs/config.py
linea_cli-0.1.0.dist-info/METADATA
linea_cli-0.1.0.dist-info/WHEEL
linea_cli-0.1.0.dist-info/entry_points.txt
linea_cli-0.1.0.dist-info/top_level.txt
linea_cli-0.1.0.dist-info/RECORD
