Metadata-Version: 2.1
Name: linea-cli
Version: 0.1.0
Summary: The Linea Software Command Line is a lightweight interface to interact with the Linea Platform
Author-email: Linea Labs <dev@linea.ai>
Maintainer-email: Linea Labs <dev@linea.ai>
Project-URL: Homepage, https://linea.ai
Project-URL: Repository, https://github.com/LineaLabs/gentoo/cli
Classifier: Development Status :: 2 - Pre-Alpha
Classifier: Programming Language :: Python :: 3.9
Classifier: Intended Audience :: Developers
Classifier: Topic :: Software Development :: Debuggers
Requires-Python: >=3.9
Requires-Dist: typer[all] ==0.9.0
Requires-Dist: requests ==2.31.0
